odoo10_addon_l10n_it_withholding_tax_causali-10.0.1.0.0.99.dev7-py3.8-nspkg.pth
odoo/addons/l10n_it_withholding_tax_causali/README.rst
odoo/addons/l10n_it_withholding_tax_causali/__init__.py
odoo/addons/l10n_it_withholding_tax_causali/__manifest__.py
odoo/addons/l10n_it_withholding_tax_causali/i18n/it.po
odoo/addons/l10n_it_withholding_tax_causali/i18n/l10n_it_withholding_tax_causali.pot
odoo/addons/l10n_it_withholding_tax_causali/models/__init__.py
odoo/addons/l10n_it_withholding_tax_causali/models/withholding_tax.py
odoo/addons/l10n_it_withholding_tax_causali/readme/DESCRIPTION.rst
odoo/addons/l10n_it_withholding_tax_causali/static/description/icon.png
odoo/addons/l10n_it_withholding_tax_causali/static/description/index.html
odoo/addons/l10n_it_withholding_tax_causali/views/withholding_tax.xml
odoo10_addon_l10n_it_withholding_tax_causali-10.0.1.0.0.99.dev7.dist-info/METADATA
odoo10_addon_l10n_it_withholding_tax_causali-10.0.1.0.0.99.dev7.dist-info/WHEEL
odoo10_addon_l10n_it_withholding_tax_causali-10.0.1.0.0.99.dev7.dist-info/namespace_packages.txt
odoo10_addon_l10n_it_withholding_tax_causali-10.0.1.0.0.99.dev7.dist-info/top_level.txt
odoo10_addon_l10n_it_withholding_tax_causali-10.0.1.0.0.99.dev7.dist-info/RECORD
