Metadata-Version: 2.1
Name: odoo10-addon-l10n-it-withholding-tax-causali
Version: 10.0.1.0.0.99.dev7
Summary: Causali pagamento per ritenute d'acconto
Home-page: https://github.com/OCA/l10n-italy
Author: Agile Business Group, Odoo Community Association (OCA)
Author-email: support@odoo-community.org
License: LGPL-3
Platform: UNKNOWN
Classifier: Programming Language :: Python
Classifier: Framework :: Odoo
Classifier: Framework :: Odoo :: 10.0
Classifier: License :: OSI Approved :: GNU Lesser General Public License v3 (LGPLv3)
Classifier: Development Status :: 4 - Beta
Requires-Python: ~=2.7
Requires-Dist: odoo10-addon-l10n-it-causali-pagamento
Requires-Dist: odoo10-addon-l10n-it-withholding-tax
Requires-Dist: odoo <10.1dev,>=10.0
